MANIFEST.in
README.md
setup.py
django_moreforms.egg-info/PKG-INFO
django_moreforms.egg-info/SOURCES.txt
django_moreforms.egg-info/dependency_links.txt
django_moreforms.egg-info/top_level.txt
moreforms/__init__.py
moreforms/forms.py
moreforms/models.py
moreforms/date/__init__.py
moreforms/date/exceptions.py
moreforms/date/fields.py
moreforms/date/widgets.py
moreforms/fancy/__init__.py
moreforms/fancy/fields.py
moreforms/fancy/widgets.py
moreforms/fieldtree/__init__.py
moreforms/fieldtree/fields.py
moreforms/fieldtree/fieldtree.py
moreforms/fieldtree/widgets.py
moreforms/templatetags/__init__.py
moreforms/templatetags/moreforms.py
static/moreforms/fields.js