Metadata-Version: 1.0
Name: django-moreforms
Version: 1.2
Summary: Contains helpful fields for Django, such as a FieldTree (a simple way to get a field chain) and date-related fields.
Home-page: UNKNOWN
Author: Jordan Nath
Author-email: jordannh@sent.com
License: UNKNOWN
Platform: UNKNOWN
